{
    "title": "Stages and Pipelines",
    "description": "Process data and generate outputs in a reproducible way.",
    "difficulty": "Beginner",
    "time": "15-25 min",
    "details": {
        "steps": [
            {
                "title": "Step 1",
                "text": "01-manual-data-preparation.md"
            },
            {
                "title": "Step 2",
                "text": "02-adding-a-stage.md"
            },
            {
                "title": "Step 3",
                "text": "03-running-a-stage.md"
            },
            {
                "title": "Step 4",
                "text": "04-how-dvc-tracks-stages.md"
            },
            {
                "title": "Step 5",
                "text": "05-add-featurization-stage.md"
            },
            {
                "title": "Step 6",
                "text": "06-reproduce-a-pipeline.md"
            },
            {
                "title": "Step 7",
                "text": "07-visualize-the-pipeline.md"
            },
            {
                "title": "Congratulations!",
                "text": "08-ending.md"
            }
        ],
        "intro": {
            "text": "intro.md",
            "credits": "https://dvc.org/doc/start/data-pipelines",
            "courseData": "install.sh",
            "code": "init.sh"
        },
        "assets": {
            "host01": [
                {
                    "file": "prepare.sh",
                    "target": "/usr/local/bin/",
                    "chmod": "+x"
                },
                {
                    "file": "play",
                    "target": "/usr/local/bin/",
                    "chmod": "+x"
                },
                {
                    "file": "params.yaml",
                    "target": "/root/project"
                },
                {
                    "file": "src",
                    "target": "/root/project/"
                }
            ]
        }
    },
    "environment": {
        "uieditorpath": "/root/project",
        "uilayout": "editor-terminal"
    },
    "backend": {
        "imageid": "ubuntu:2004"
    }
}
